index.py
failure_invoker_mcp-1.1.0.dist-info/licenses/LICENSE
validate/validator.py
failure_invoker_mcp-1.1.0.dist-info/METADATA
failure_invoker_mcp-1.1.0.dist-info/WHEEL
failure_invoker_mcp-1.1.0.dist-info/entry_points.txt
failure_invoker_mcp-1.1.0.dist-info/top_level.txt
failure_invoker_mcp-1.1.0.dist-info/RECORD
